Workbook

Sheet PROTOCOLO
C1: Protocolo de Viabilidad Económica de Educación Posgraduada | W1: Código | X1: FPI.DP-01 v.02
W2: Página | X2: 1 de 1
A6: DATOS DE MATRÍCULA | E6: PROGRAMA | F6: CRÉDITO smlv | I6: Aspirantes con Descuentos Institucionales | O6: Incripciones (solo primer semestre) | Q6: Especializaciones,Maestrias y Doctorados 0,16% SMMLV | T6: Nivel del programa de Posgrado | V6: Valor del credito | W6: Valor a pagar por crédito
A7: S.M.M.L.V | E7: Doctorado - 0,88 SMMLV | F7: =(C7*0.88) -> 0 | I7: (Egresado, Certificado Electoral, Convención Colectiva)
A8: Valor de la Matrícula | C8: =F9*C9 -> 0 | E8: Maestría - 0,54 SMMLV | F8: =(C7*0.54) -> 0 | I8: Porcentaje del Descuento | J8: Numero de Aspirantes | K8: $ Ingresos con Descuento | O8: $ Valor Inscripción | Q8: Numero de Aspirantes | R8: $ Ingresos por Inscripción | T8: ESPECIALIZACION | V8: 1.37 smmlv | W8: =(1423500*1.37) -> 1950195
A9: Número de créditos por semestre | E9: Especialización - 0,34 SMMLV | F9: =(C7*0.34) -> 0 | K9: =(C8*J9)-((C8*I9)*J9) -> 0 | O9: =C7*16% -> 0 | R9: =O9*Q9 -> 0 | T9: MAESTRIA | V9: 1.51 smmlv | W9: =(1423500*1.51) -> 2149485
K10: =(C8*J10)-((C8*I10)*J10) -> 0 | O10: TOTAL | Q10: =SUM(Q9) -> 0 | R10: =SUM(R9) -> 0 | T10: DOCTORADO | V10: 1.87 smmlv | W10: =(1423500*1.87) -> 2661945
K11: =(C8*J11)-((C8*I11)*J11) -> 0
A12: DATOS BASICOS | K12: =(C8*J12)-((C8*I12)*J12) -> 0
A13: FACULTAD | K13: =(C8*J13)-((C8*I13)*J13) -> 0 | M13: Derechos de grado aplica solo para Últimos Semestres
A14: NOMBRE DEL PROGRAMA: | F14: CDP | K14: =(C8*J14)-((C8*I14)*J14) -> 0 | O14: CONSOLIDADO DE INGRESOS
A15: COHORTE - SEMESTRE | K15: =(C8*J15)-((C8*I15)*J15) -> 0 | M15: $ Total Ingresos | O15: $ Ingresos Total por Inscripciones | P15: $ Ingresos Total por Timbre Procultura | Q15: $ Ingresos Total por Seguro Estudiantil | R15: $ Ingresos Total por Matricula
A16: CIUDAD A REALIZAR LA ACTIVIDAD: | K16: =(C8*J16)-((C8*I16)*J16) -> 0 | M16: =#REF!+#REF!+#REF! -> #REF! | O16: =R10 -> 0 | P16: =C7*2%*J17 -> 0 | Q16: =(17000*J17) -> 0 | R16: =K17 -> 0
A17: DIRECTOR DEL PROGRAMA: | I17: TOTAL | J17: =SUM(J9:J16) -> 0 | K17: =SUM(K9:K16) -> 0
A20: N° | B20: Nombre del Seminario, Curso o Conferencia | C20: Fecha del seminario (Colocar la fecha en letras) | E20: Docentes Nombres y Apellidos Completos | F20: Tipo de Vinculacion (docente o administrativo) | G20: Nacionalidad Colombiano o extranjero | H20: Tipo de Identificación ( C.C o C.E.) | I20: Número de Documento de Identificación | J20: Dirección | K20: Teléfono | L20: Grado de escolaridad | O20: Valor Crédito | P20: #Créditos | Q20: Valor de los Honorarios | R20: Transporte Aéreo | S20: Destino Ida y Vuelta del Transporte Aereo (Indicar Ruta) | T20: $ Transporte Terrestre | U20: Destino ida y vuelta del transporte terrestre (Indicar Ruta) | V20: $ Auxilio de Alimento y Hospedaje | W20: Días de estadía en la ciudad del evento | X20: HOTEL (Ciudad donde se prestará el servicio de hospedaje)
A21: BONIFICACIONES ( PLANTA Y ADMINISTRATIVOS)
A23: TOTAL
A25: DOCENTE EXTERNO(OPS)
A27: TOTAL | AA27: =SUM(#REF!) -> #REF!
B28: NOTA: Los datos suministrados en el protocolo son responsabilidad de los Directores de los programas de Postgrados. La División Administrativa de Postgrados no sea hace responsable si estos datos no son reales.

Sheet VIABILIDAD
C2: Protocolo de Viabilidad Económica de Educacion Posgraduada | I2: Código | J2: FPI.DP-01 v.02
I3: Página | J3: 2 de 2
B6: Efectuados los trámites pertinentes por parte del director(a) del programa: | F6: =PROTOCOLO!C14 -> 0
B7: COHORTE: | C7: =C13 -> 0 | D7: SEMESTRE: | E7: =PROTOCOLO!E15 -> 0 | F7: a dictarse en la ciudad de | G7: =PROTOCOLO!C16 -> 0
B8: ha cumplido con los requisitos minimos establecios en el protocolo de viabilidad económica, conforme a los siguientes aspectos:
C11: =PROTOCOLO!C13 -> 0
C12: =PROTOCOLO!C14 -> 0
C13: =PROTOCOLO!C15 -> 0
C14: =PROTOCOLO!E15 -> 0
C16: INGRESOS
C18: Valor del SMMLV | I18: =PROTOCOLO!C7 -> 0
C19: Inscripciones | I19: =PROTOCOLO!R10 -> 0
C20: Ingreso Matrículas | I20: =PROTOCOLO!K17 -> 0
C21: Estampilla Procultura | I21: =PROTOCOLO!P16 -> 0
C22: Seguro estudiantil | I22: =PROTOCOLO!Q16 -> 0
C23: Total Recaudado a la Fecha por Matriculas (Según Factibilidad del Sistema) | I23: =I20 -> 0
C24: Total a Recaudar por semestre (Ingreso Matriculas + Inscripciones (Si hay)) | I24: =I19+I20+I21+I22 -> 0
C26: EGRESOS
C27: Honorarios Docentes | I27: =PROTOCOLO!Q27 -> 0
C28: BONIFICACIONES | I28: =PROTOCOLO!Q23 -> 0
C29: Alojamiento | I29: =PROTOCOLO!V27 -> 0
C30: Transporte Aéreo | I30: =PROTOCOLO!R27 -> 0
C31: Transporte Terrestre | I31: =PROTOCOLO!T27 -> 0
C32: Otros | I32: =PROTOCOLO!K17*35% -> 0
C33: Estampilla Procultura | I33: =I21 -> 0
C35: Total Egresos Para CDP | I35: =SUM(I27:I34) -> 0
C37: Utilidad | I37: =I24-I35 -> 0
C38: % Utilidad | I38: =(I37/I24) -> #DIV/0!
C41: Se expide la presente a los | F41: días del mes de | H41: del
C51: Director(a) Oficina de Planeación
C53: Nota: Este documento es requisito indispensable para:
C54: *Solicitud y Expedición del Certificado de Disponibilidad Presupuestal
C55: *Efectuar Pago de docentes
C56: *Dar inicio al programa en mención

Sheet LISTA DE ESTUDIANTES
B1: No. | C1: NOMBRE COMPLETO | D1: CEDULA | E1: DESCUENTOS Marcar con una X la casilla correspondiente - Sólo se puede aplicar a 2 descuentos
E2: EGRESADO | F2: ELECTORAL | G2: DOCENTE | I2: ADMINISTRATIVOS | J2: CAJA DE COMPESACIÓN | L2: OPS | M2: PREPOSGRADO | N2: BECA | O2: TOTAL % DESCUENTOS
E3: 0.15 | F3: 0.1 | G3: TCO/HC 30% | H3: PLANTA 95% | I3: 0.95 | J3: COMFA NORTE 15% | K3: COMFA ORIENTE 15% | L3: 0.4 | M3: 0.5 | N3: 1
B4: 1
B5: 2
B6: 3
B7: 4
B8: 5
B9: 6
B10: 7
B11: 8
B12: 9
B13: 10
B14: 11
B15: 12
... B41: 38
